[{"distance":2.27,"time":4,"hospital":{"hospitalId":10,"hospitalName":"The Portland Hospital for Women and Children","hospitalLatitude":51.522471,"hospitalLongitude":-0.143586,"bedSet":[{"bedId":8502,"bedCode":"10-74-B151","speciality":{"specialityId":74,"specialityName":"Chirurgie cardiothoracique"},"free":true},{"bedId":8501,"bedCode":"10-72-B150","speciality":{"specialityId":72,"specialityName":"Radiologie clinique"},"free":true},{"bedId":8497,"bedCode":"10-64-B146","speciality":{"specialityId":64,"specialityName":"Rhumatologie"},"free":true},{"bedId":8504,"bedCode":"10-78-B153","speciality":{"specialityId":78,"specialityName":"Otolaryngologie"},"free":true},{"bedId":8481,"bedCode":"10-32-B130","speciality":{"specialityId":32,"specialityName":"Orthodontie"},"free":true},{"bedId":8478,"bedCode":"10-26-B127","speciality":{"specialityId":26,"specialityName":"Radiologie dentaire et maxillo-faciale"},"free":true},{"bedId":8483,"bedCode":"10-36-B132","speciality":{"specialityId":36,"specialityName":"Dentisterie restauratrice"},"free":true},{"bedId":8493,"bedCode":"10-56-B142","speciality":{"specialityId":56,"specialityName":"Ophtalmologie médicale"},"free":true},{"bedId":8495,"bedCode":"10-60-B144","speciality":{"specialityId":60,"specialityName":"Médecine palliative"},"free":true},{"bedId":8479,"bedCode":"10-28-B128","speciality":{"specialityId":28,"specialityName":"Chirurgie buccale et maxillo-faciale"},"free":true},{"bedId":8476,"bedCode":"10-22-B125","speciality":{"specialityId":22,"specialityName":"Anesthésie"},"free":false},{"bedId":8489,"bedCode":"10-48-B138","speciality":{"specialityId":48,"specialityName":"Gastroentérologie"},"free":true},{"bedId":8484,"bedCode":"10-38-B133","speciality":{"specialityId":38,"specialityName":"Médecine d'urgence"},"free":false},{"bedId":8480,"bedCode":"10-30-B129","speciality":{"specialityId":30,"specialityName":"Médecine buccale"},"free":true},{"bedId":8506,"bedCode":"10-82-B155","speciality":{"specialityId":82,"specialityName":"Urologie"},"free":true},{"bedId":8488,"bedCode":"10-46-B137","speciality":{"specialityId":46,"specialityName":"Dermatologie"},"free":true},{"bedId":8487,"bedCode":"10-44-B136","speciality":{"specialityId":44,"specialityName":"Neurophysiologie clinique"},"free":true},{"bedId":8505,"bedCode":"10-80-B154","speciality":{"specialityId":80,"specialityName":"Chirurgie plastique"},"free":true},{"bedId":8491,"bedCode":"10-52-B140","speciality":{"specialityId":52,"specialityName":"Médecine génito-urinaire"},"free":true},{"bedId":8496,"bedCode":"10-62-B145","speciality":{"specialityId":62,"specialityName":"Médecine rénale"},"free":true},{"bedId":8485,"bedCode":"10-40-B134","speciality":{"specialityId":40,"specialityName":"Allergie"},"free":true},{"bedId":8503,"bedCode":"10-76-B152","speciality":{"specialityId":76,"specialityName":"Neurochirurgie"},"free":true},{"bedId":8494,"bedCode":"10-58-B143","speciality":{"specialityId":58,"specialityName":"Médecine du travail"},"free":true},{"bedId":8490,"bedCode":"10-50-B139","speciality":{"specialityId":50,"specialityName":"Médecine générale"},"free":true},{"bedId":8477,"bedCode":"10-24-B126","speciality":{"specialityId":24,"specialityName":"Oncologie clinique"},"free":false},{"bedId":8486,"bedCode":"10-42-B135","speciality":{"specialityId":42,"specialityName":"Cardiologie"},"free":true},{"bedId":8482,"bedCode":"10-34-B131","speciality":{"specialityId":34,"specialityName":"Parodontie"},"free":true},{"bedId":8492,"bedCode":"10-54-B141","speciality":{"specialityId":54,"specialityName":"Maladies infectieuses"},"free":true},{"bedId":8498,"bedCode":"10-66-B147","speciality":{"specialityId":66,"specialityName":"Santé publique sexuelle et procréative"},"free":true},{"bedId":8499,"bedCode":"10-68-B148","speciality":{"specialityId":68,"specialityName":"Pédiatrie"},"free":false},{"bedId":8500,"bedCode":"10-70-B149","speciality":{"specialityId":70,"specialityName":"Psychiatrie des troubles d'apprentissage"},"free":true}]},"bedId":8482,"bedCode":"10-34-B131"},{"distance":14.68,"time":24,"hospital":{"hospitalId":4,"hospitalName":"British Home & Hospital for Incurables","hospitalLatitude":51.423089,"hospitalLongitude":-0.107068,"bedSet":[{"bedId":8413,"bedCode":"4-82-B62","speciality":{"specialityId":82,"specialityName":"Urologie"},"free":true},{"bedId":8397,"bedCode":"4-50-B46","speciality":{"specialityId":50,"specialityName":"Médecine générale"},"free":true},{"bedId":8411,"bedCode":"4-78-B60","speciality":{"specialityId":78,"specialityName":"Otolaryngologie"},"free":true},{"bedId":8401,"bedCode":"4-58-B50","speciality":{"specialityId":58,"specialityName":"Médecine du travail"},"free":true},{"bedId":8403,"bedCode":"4-62-B52","speciality":{"specialityId":62,"specialityName":"Médecine rénale"},"free":true},{"bedId":8407,"bedCode":"4-70-B56","speciality":{"specialityId":70,"specialityName":"Psychiatrie des troubles d'apprentissage"},"free":true},{"bedId":8410,"bedCode":"4-76-B59","speciality":{"specialityId":76,"specialityName":"Neurochirurgie"},"free":true},{"bedId":8398,"bedCode":"4-52-B47","speciality":{"specialityId":52,"specialityName":"Médecine génito-urinaire"},"free":true},{"bedId":8394,"bedCode":"4-44-B43","speciality":{"specialityId":44,"specialityName":"Neurophysiologie clinique"},"free":true},{"bedId":8383,"bedCode":"4-22-B32","speciality":{"specialityId":22,"specialityName":"Anesthésie"},"free":false},{"bedId":8392,"bedCode":"4-40-B41","speciality":{"specialityId":40,"specialityName":"Allergie"},"free":true},{"bedId":8388,"bedCode":"4-32-B37","speciality":{"specialityId":32,"specialityName":"Orthodontie"},"free":true},{"bedId":8412,"bedCode":"4-80-B61","speciality":{"specialityId":80,"specialityName":"Chirurgie plastique"},"free":true},{"bedId":8390,"bedCode":"4-36-B39","speciality":{"specialityId":36,"specialityName":"Dentisterie restauratrice"},"free":true},{"bedId":8405,"bedCode":"4-66-B54","speciality":{"specialityId":66,"specialityName":"Santé publique sexuelle et procréative"},"free":true},{"bedId":8402,"bedCode":"4-60-B51","speciality":{"specialityId":60,"specialityName":"Médecine palliative"},"free":true},{"bedId":8408,"bedCode":"4-72-B57","speciality":{"specialityId":72,"specialityName":"Radiologie clinique"},"free":true},{"bedId":8399,"bedCode":"4-54-B48","speciality":{"specialityId":54,"specialityName":"Maladies infectieuses"},"free":true},{"bedId":8406,"bedCode":"4-68-B55","speciality":{"specialityId":68,"specialityName":"Pédiatrie"},"free":true},{"bedId":8396,"bedCode":"4-48-B45","speciality":{"specialityId":48,"specialityName":"Gastroentérologie"},"free":true},{"bedId":8400,"bedCode":"4-56-B49","speciality":{"specialityId":56,"specialityName":"Ophtalmologie médicale"},"free":true},{"bedId":8391,"bedCode":"4-38-B40","speciality":{"specialityId":38,"specialityName":"Médecine d'urgence"},"free":true},{"bedId":8404,"bedCode":"4-64-B53","speciality":{"specialityId":64,"specialityName":"Rhumatologie"},"free":true},{"bedId":8384,"bedCode":"4-24-B33","speciality":{"specialityId":24,"specialityName":"Oncologie clinique"},"free":false},{"bedId":8393,"bedCode":"4-42-B42","speciality":{"specialityId":42,"specialityName":"Cardiologie"},"free":true},{"bedId":8387,"bedCode":"4-30-B36","speciality":{"specialityId":30,"specialityName":"Médecine buccale"},"free":true},{"bedId":8389,"bedCode":"4-34-B38","speciality":{"specialityId":34,"specialityName":"Parodontie"},"free":true},{"bedId":8409,"bedCode":"4-74-B58","speciality":{"specialityId":74,"specialityName":"Chirurgie cardiothoracique"},"free":true},{"bedId":8385,"bedCode":"4-26-B34","speciality":{"specialityId":26,"specialityName":"Radiologie dentaire et maxillo-faciale"},"free":true},{"bedId":8386,"bedCode":"4-28-B35","speciality":{"specialityId":28,"specialityName":"Chirurgie buccale et maxillo-faciale"},"free":true},{"bedId":8395,"bedCode":"4-46-B44","speciality":{"specialityId":46,"specialityName":"Dermatologie"},"free":true}]},"bedId":8389,"bedCode":"4-34-B38"},{"distance":15.09,"time":25,"hospital":{"hospitalId":2,"hospitalName":"Priory Hospital","hospitalLatitude":51.632064,"hospitalLongitude":-0.118304,"bedSet":[{"bedId":8370,"bedCode":"2-58-B19","speciality":{"specialityId":58,"specialityName":"Médecine du travail"},"free":true},{"bedId":8375,"bedCode":"2-68-B24","speciality":{"specialityId":68,"specialityName":"Pédiatrie"},"free":true},{"bedId":8380,"bedCode":"2-78-B29","speciality":{"specialityId":78,"specialityName":"Otolaryngologie"},"free":true},{"bedId":8361,"bedCode":"2-40-B10","speciality":{"specialityId":40,"specialityName":"Allergie"},"free":true},{"bedId":8358,"bedCode":"2-34-B7","speciality":{"specialityId":34,"specialityName":"Parodontie"},"free":true},{"bedId":8367,"bedCode":"2-52-B16","speciality":{"specialityId":52,"specialityName":"Médecine génito-urinaire"},"free":true},{"bedId":8363,"bedCode":"2-44-B12","speciality":{"specialityId":44,"specialityName":"Neurophysiologie clinique"},"free":true},{"bedId":8355,"bedCode":"2-28-B4","speciality":{"specialityId":28,"specialityName":"Chirurgie buccale et maxillo-faciale"},"free":true},{"bedId":8366,"bedCode":"2-50-B15","speciality":{"specialityId":50,"specialityName":"Médecine générale"},"free":true},{"bedId":8374,"bedCode":"2-66-B23","speciality":{"specialityId":66,"specialityName":"Santé publique sexuelle et procréative"},"free":true},{"bedId":8377,"bedCode":"2-72-B26","speciality":{"specialityId":72,"specialityName":"Radiologie clinique"},"free":true},{"bedId":8376,"bedCode":"2-70-B25","speciality":{"specialityId":70,"specialityName":"Psychiatrie des troubles d'apprentissage"},"free":true},{"bedId":8378,"bedCode":"2-74-B27","speciality":{"specialityId":74,"specialityName":"Chirurgie cardiothoracique"},"free":true},{"bedId":8353,"bedCode":"2-24-B2","speciality":{"specialityId":24,"specialityName":"Oncologie clinique"},"free":false},{"bedId":8368,"bedCode":"2-54-B17","speciality":{"specialityId":54,"specialityName":"Maladies infectieuses"},"free":true},{"bedId":8372,"bedCode":"2-62-B21","speciality":{"specialityId":62,"specialityName":"Médecine rénale"},"free":true},{"bedId":8362,"bedCode":"2-42-B11","speciality":{"specialityId":42,"specialityName":"Cardiologie"},"free":true},{"bedId":8357,"bedCode":"2-32-B6","speciality":{"specialityId":32,"specialityName":"Orthodontie"},"free":true},{"bedId":8379,"bedCode":"2-76-B28","speciality":{"specialityId":76,"specialityName":"Neurochirurgie"},"free":true},{"bedId":8371,"bedCode":"2-60-B20","speciality":{"specialityId":60,"specialityName":"Médecine palliative"},"free":true},{"bedId":8354,"bedCode":"2-26-B3","speciality":{"specialityId":26,"specialityName":"Radiologie dentaire et maxillo-faciale"},"free":true},{"bedId":8359,"bedCode":"2-36-B8","speciality":{"specialityId":36,"specialityName":"Dentisterie restauratrice"},"free":true},{"bedId":8381,"bedCode":"2-80-B30","speciality":{"specialityId":80,"specialityName":"Chirurgie plastique"},"free":true},{"bedId":8356,"bedCode":"2-30-B5","speciality":{"specialityId":30,"specialityName":"Médecine buccale"},"free":true},{"bedId":8369,"bedCode":"2-56-B18","speciality":{"specialityId":56,"specialityName":"Ophtalmologie médicale"},"free":true},{"bedId":8360,"bedCode":"2-38-B9","speciality":{"specialityId":38,"specialityName":"Médecine d'urgence"},"free":true},{"bedId":8364,"bedCode":"2-46-B13","speciality":{"specialityId":46,"specialityName":"Dermatologie"},"free":true},{"bedId":8352,"bedCode":"2-22-B1","speciality":{"specialityId":22,"specialityName":"Anesthésie"},"free":false},{"bedId":8365,"bedCode":"2-48-B14","speciality":{"specialityId":48,"specialityName":"Gastroentérologie"},"free":true},{"bedId":8382,"bedCode":"2-82-B31","speciality":{"specialityId":82,"specialityName":"Urologie"},"free":true},{"bedId":8373,"bedCode":"2-64-B22","speciality":{"specialityId":64,"specialityName":"Rhumatologie"},"free":true}]},"bedId":8358,"bedCode":"2-34-B7"},{"distance":17.72,"time":28,"hospital":{"hospitalId":8,"hospitalName":"Chapel Orchard Day Surgery","hospitalLatitude":51.402049,"hospitalLongitude":-0.171537,"bedSet":[{"bedId":8468,"bedCode":"8-68-B117","speciality":{"specialityId":68,"specialityName":"Pédiatrie"},"free":true},{"bedId":8456,"bedCode":"8-44-B105","speciality":{"specialityId":44,"specialityName":"Neurophysiologie clinique"},"free":true},{"bedId":8462,"bedCode":"8-56-B111","speciality":{"specialityId":56,"specialityName":"Ophtalmologie médicale"},"free":true},{"bedId":8450,"bedCode":"8-32-B99","speciality":{"specialityId":32,"specialityName":"Orthodontie"},"free":true},{"bedId":8458,"bedCode":"8-48-B107","speciality":{"specialityId":48,"specialityName":"Gastroentérologie"},"free":true},{"bedId":8470,"bedCode":"8-72-B119","speciality":{"specialityId":72,"specialityName":"Radiologie clinique"},"free":true},{"bedId":8455,"bedCode":"8-42-B104","speciality":{"specialityId":42,"specialityName":"Cardiologie"},"free":true},{"bedId":8463,"bedCode":"8-58-B112","speciality":{"specialityId":58,"specialityName":"Médecine du travail"},"free":true},{"bedId":8453,"bedCode":"8-38-B102","speciality":{"specialityId":38,"specialityName":"Médecine d'urgence"},"free":true},{"bedId":8457,"bedCode":"8-46-B106","speciality":{"specialityId":46,"specialityName":"Dermatologie"},"free":true},{"bedId":8446,"bedCode":"8-24-B95","speciality":{"specialityId":24,"specialityName":"Oncologie clinique"},"free":false},{"bedId":8472,"bedCode":"8-76-B121","speciality":{"specialityId":76,"specialityName":"Neurochirurgie"},"free":true},{"bedId":8459,"bedCode":"8-50-B108","speciality":{"specialityId":50,"specialityName":"Médecine générale"},"free":true},{"bedId":8449,"bedCode":"8-30-B98","speciality":{"specialityId":30,"specialityName":"Médecine buccale"},"free":true},{"bedId":8451,"bedCode":"8-34-B100","speciality":{"specialityId":34,"specialityName":"Parodontie"},"free":true},{"bedId":8473,"bedCode":"8-78-B122","speciality":{"specialityId":78,"specialityName":"Otolaryngologie"},"free":true},{"bedId":8469,"bedCode":"8-70-B118","speciality":{"specialityId":70,"specialityName":"Psychiatrie des troubles d'apprentissage"},"free":true},{"bedId":8474,"bedCode":"8-80-B123","speciality":{"specialityId":80,"specialityName":"Chirurgie plastique"},"free":true},{"bedId":8465,"bedCode":"8-62-B114","speciality":{"specialityId":62,"specialityName":"Médecine rénale"},"free":true},{"bedId":8447,"bedCode":"8-26-B96","speciality":{"specialityId":26,"specialityName":"Radiologie dentaire et maxillo-faciale"},"free":true},{"bedId":8464,"bedCode":"8-60-B113","speciality":{"specialityId":60,"specialityName":"Médecine palliative"},"free":true},{"bedId":8445,"bedCode":"8-22-B94","speciality":{"specialityId":22,"specialityName":"Anesthésie"},"free":false},{"bedId":8448,"bedCode":"8-28-B97","speciality":{"specialityId":28,"specialityName":"Chirurgie buccale et maxillo-faciale"},"free":true},{"bedId":8466,"bedCode":"8-64-B115","speciality":{"specialityId":64,"specialityName":"Rhumatologie"},"free":true},{"bedId":8460,"bedCode":"8-52-B109","speciality":{"specialityId":52,"specialityName":"Médecine génito-urinaire"},"free":true},{"bedId":8454,"bedCode":"8-40-B103","speciality":{"specialityId":40,"specialityName":"Allergie"},"free":true},{"bedId":8452,"bedCode":"8-36-B101","speciality":{"specialityId":36,"specialityName":"Dentisterie restauratrice"},"free":true},{"bedId":8461,"bedCode":"8-54-B110","speciality":{"specialityId":54,"specialityName":"Maladies infectieuses"},"free":true},{"bedId":8467,"bedCode":"8-66-B116","speciality":{"specialityId":66,"specialityName":"Santé publique sexuelle et procréative"},"free":true},{"bedId":8471,"bedCode":"8-74-B120","speciality":{"specialityId":74,"specialityName":"Chirurgie cardiothoracique"},"free":true},{"bedId":8475,"bedCode":"8-82-B124","speciality":{"specialityId":82,"specialityName":"Urologie"},"free":true}]},"bedId":8451,"bedCode":"8-34-B100"},{"distance":21.5,"time":33,"hospital":{"hospitalId":6,"hospitalName":"Sloane Hospital","hospitalLatitude":51.408204,"hospitalLongitude":-0.00454,"bedSet":[{"bedId":8441,"bedCode":"6-76-B90","speciality":{"specialityId":76,"specialityName":"Neurochirurgie"},"free":true},{"bedId":8429,"bedCode":"6-52-B78","speciality":{"specialityId":52,"specialityName":"Médecine génito-urinaire"},"free":true},{"bedId":8430,"bedCode":"6-54-B79","speciality":{"specialityId":54,"specialityName":"Maladies infectieuses"},"free":true},{"bedId":8416,"bedCode":"6-26-B65","speciality":{"specialityId":26,"specialityName":"Radiologie dentaire et maxillo-faciale"},"free":true},{"bedId":8428,"bedCode":"6-50-B77","speciality":{"specialityId":50,"specialityName":"Médecine générale"},"free":true},{"bedId":8438,"bedCode":"6-70-B87","speciality":{"specialityId":70,"specialityName":"Psychiatrie des troubles d'apprentissage"},"free":true},{"bedId":8415,"bedCode":"6-24-B64","speciality":{"specialityId":24,"specialityName":"Oncologie clinique"},"free":true},{"bedId":8443,"bedCode":"6-80-B92","speciality":{"specialityId":80,"specialityName":"Chirurgie plastique"},"free":true},{"bedId":8434,"bedCode":"6-62-B83","speciality":{"specialityId":62,"specialityName":"Médecine rénale"},"free":true},{"bedId":8425,"bedCode":"6-44-B74","speciality":{"specialityId":44,"specialityName":"Neurophysiologie clinique"},"free":true},{"bedId":8436,"bedCode":"6-66-B85","speciality":{"specialityId":66,"specialityName":"Santé publique sexuelle et procréative"},"free":true},{"bedId":8420,"bedCode":"6-34-B69","speciality":{"specialityId":34,"specialityName":"Parodontie"},"free":true},{"bedId":8431,"bedCode":"6-56-B80","speciality":{"specialityId":56,"specialityName":"Ophtalmologie médicale"},"free":true},{"bedId":8440,"bedCode":"6-74-B89","speciality":{"specialityId":74,"specialityName":"Chirurgie cardiothoracique"},"free":true},{"bedId":8442,"bedCode":"6-78-B91","speciality":{"specialityId":78,"specialityName":"Otolaryngologie"},"free":true},{"bedId":8433,"bedCode":"6-60-B82","speciality":{"specialityId":60,"specialityName":"Médecine palliative"},"free":true},{"bedId":8421,"bedCode":"6-36-B70","speciality":{"specialityId":36,"specialityName":"Dentisterie restauratrice"},"free":true},{"bedId":8439,"bedCode":"6-72-B88","speciality":{"specialityId":72,"specialityName":"Radiologie clinique"},"free":true},{"bedId":8426,"bedCode":"6-46-B75","speciality":{"specialityId":46,"specialityName":"Dermatologie"},"free":true},{"bedId":8424,"bedCode":"6-42-B73","speciality":{"specialityId":42,"specialityName":"Cardiologie"},"free":true},{"bedId":8435,"bedCode":"6-64-B84","speciality":{"specialityId":64,"specialityName":"Rhumatologie"},"free":true},{"bedId":8418,"bedCode":"6-30-B67","speciality":{"specialityId":30,"specialityName":"Médecine buccale"},"free":true},{"bedId":8437,"bedCode":"6-68-B86","speciality":{"specialityId":68,"specialityName":"Pédiatrie"},"free":true},{"bedId":8432,"bedCode":"6-58-B81","speciality":{"specialityId":58,"specialityName":"Médecine du travail"},"free":true},{"bedId":8417,"bedCode":"6-28-B66","speciality":{"specialityId":28,"specialityName":"Chirurgie buccale et maxillo-faciale"},"free":true},{"bedId":8419,"bedCode":"6-32-B68","speciality":{"specialityId":32,"specialityName":"Orthodontie"},"free":true},{"bedId":8444,"bedCode":"6-82-B93","speciality":{"specialityId":82,"specialityName":"Urologie"},"free":true},{"bedId":8427,"bedCode":"6-48-B76","speciality":{"specialityId":48,"specialityName":"Gastroentérologie"},"free":true},{"bedId":8414,"bedCode":"6-22-B63","speciality":{"specialityId":22,"specialityName":"Anesthésie"},"free":false},{"bedId":8422,"bedCode":"6-38-B71","speciality":{"specialityId":38,"specialityName":"Médecine d'urgence"},"free":true},{"bedId":8423,"bedCode":"6-40-B72","speciality":{"specialityId":40,"specialityName":"Allergie"},"free":true}]},"bedId":8420,"bedCode":"6-34-B69"}]